logstash_logging/__init__.py
logstash_logging/enums.py
logstash_logging/formatter.py
logstash_logging/logstash_logger.py
tests/__init__.py
tests/test_logstash_logger.py
hyprbots_logging_framework-0.1.0.dist-info/METADATA
hyprbots_logging_framework-0.1.0.dist-info/WHEEL
hyprbots_logging_framework-0.1.0.dist-info/top_level.txt
hyprbots_logging_framework-0.1.0.dist-info/RECORD
