Metadata-Version: 2.1
Name: hyprbots-logging-framework
Version: 0.1.0
Summary: A custom logging package for multiple platforms
Home-page: https://github.com/hyprbots/custom_logging
Author: Anonymous
Author-email: anonymous@xyz.com
Classifier: Programming Language :: Python :: 3
Classifier: License :: OSI Approved :: MIT License
Classifier: Operating System :: OS Independent
Requires-Python: >=3.6
Requires-Dist: python-logstash-async
